datapizza/clients/bedrock/__init__.py
datapizza/clients/bedrock/bedrock_client.py
datapizza/clients/bedrock/memory_adapter.py
datapizza_ai_clients_bedrock-0.0.3.dist-info/METADATA
datapizza_ai_clients_bedrock-0.0.3.dist-info/WHEEL
datapizza_ai_clients_bedrock-0.0.3.dist-info/RECORD
