Metadata-Version: 2.4
Name: datapizza-ai-clients-bedrock
Version: 0.0.3
Summary: AWS Bedrock client for the datapizza-ai framework
License: MIT
Classifier: License :: OSI Approved :: MIT License
Classifier: Programming Language :: Python :: 3
Classifier: Topic :: Scientific/Engineering :: Artificial Intelligence
Classifier: Topic :: Software Development :: Libraries :: Application Frameworks
Requires-Python: <4,>=3.10.0
Requires-Dist: aioboto3>=13.0.0
Requires-Dist: boto3>=1.35.0
Requires-Dist: botocore>=1.35.0
Requires-Dist: datapizza-ai-core<0.1.0,>=0.0.1
